odoo/addons/sale_discount_display_amount/README.rst
odoo/addons/sale_discount_display_amount/__init__.py
odoo/addons/sale_discount_display_amount/__manifest__.py
odoo/addons/sale_discount_display_amount/hooks.py
odoo/addons/sale_discount_display_amount/i18n/ca.po
odoo/addons/sale_discount_display_amount/i18n/de.po
odoo/addons/sale_discount_display_amount/i18n/es.po
odoo/addons/sale_discount_display_amount/i18n/es_ES.po
odoo/addons/sale_discount_display_amount/i18n/fr.po
odoo/addons/sale_discount_display_amount/i18n/it.po
odoo/addons/sale_discount_display_amount/i18n/nl.po
odoo/addons/sale_discount_display_amount/i18n/sale_discount_display_amount.pot
odoo/addons/sale_discount_display_amount/i18n/zh_CN.po
odoo/addons/sale_discount_display_amount/migrations/14.0.1.2.0/post-compute-subtotal-columns.py
odoo/addons/sale_discount_display_amount/migrations/14.0.1.2.0/pre-add-subtotal-columns.py
odoo/addons/sale_discount_display_amount/models/__init__.py
odoo/addons/sale_discount_display_amount/models/res_company.py
odoo/addons/sale_discount_display_amount/models/res_config_settings.py
odoo/addons/sale_discount_display_amount/models/sale_order.py
odoo/addons/sale_discount_display_amount/models/sale_order_line.py
odoo/addons/sale_discount_display_amount/readme/CONFIGURE.rst
odoo/addons/sale_discount_display_amount/readme/CONTRIBUTORS.rst
odoo/addons/sale_discount_display_amount/readme/DESCRIPTION.rst
odoo/addons/sale_discount_display_amount/readme/USAGE.rst
odoo/addons/sale_discount_display_amount/report/sale_report_template.xml
odoo/addons/sale_discount_display_amount/static/description/icon.png
odoo/addons/sale_discount_display_amount/static/description/index.html
odoo/addons/sale_discount_display_amount/tests/__init__.py
odoo/addons/sale_discount_display_amount/tests/test_discount_display_amount.py
odoo/addons/sale_discount_display_amount/views/res_config_settings_view.xml
odoo/addons/sale_discount_display_amount/views/sale_view.xml
odoo14_addon_sale_discount_display_amount-14.0.2.1.0.dist-info/METADATA
odoo14_addon_sale_discount_display_amount-14.0.2.1.0.dist-info/WHEEL
odoo14_addon_sale_discount_display_amount-14.0.2.1.0.dist-info/top_level.txt
odoo14_addon_sale_discount_display_amount-14.0.2.1.0.dist-info/RECORD
